{
  "label": "message.sticker",
  "signature": "0cd2da4ed24f",
  "reason": "shape_changed",
  "capturedAt": "2025-09-28T15:48:19.047Z",
  "shape": [
    "emoji",
    "file_id",
    "file_size",
    "file_unique_id",
    "height",
    "is_animated",
    "is_video",
    "set_name",
    "thumb",
    "thumb.file_id",
    "thumb.file_size",
    "thumb.file_unique_id",
    "thumb.height",
    "thumb.width",
    "thumbnail",
    "thumbnail.file_id",
    "thumbnail.file_size",
    "thumbnail.file_unique_id",
    "thumbnail.height",
    "thumbnail.width",
    "type",
    "width"
  ],
  "sample": {
    "width": 341,
    "height": 512,
    "emoji": "❤️",
    "set_name": "AnimeXOXO",
    "is_animated": false,
    "is_video": false,
    "type": "regular",
    "thumbnail": {
      "file_id": "[truncated]",
      "file_unique_id": "[truncated]",
      "file_size": "[truncated]",
      "width": "[truncated]",
      "height": "[truncated]"
    },
    "thumb": {
      "file_id": "[truncated]",
      "file_unique_id": "[truncated]",
      "file_size": "[truncated]",
      "width": "[truncated]",
      "height": "[truncated]"
    },
    "file_id": "CAACAgUAAxkBAAOFaNlFuSV08hUJD6Zssb0cJhLy6_8AAqgGAAJujF4CJeawLqunREo2BA",
    "file_unique_id": "AgADqAYAAm6MXgI",
    "file_size": 33594
  }
}
